<title></title>   
<p style="font: 11pt Times New Roman, Times, Serif; margin: 0; text-align: center">SCHEDULE 14A</p> 
<p style="font: 11pt Times New Roman, Times, Serif; margin: 0; text-align: center">Proxy Statement Pursuant to Section 14(a)</p> 
<p style="font: 11pt Times New Roman, Times, Serif; margin: 0; text-align: center">of the Securities Exchange Act of 1934</p> 
<p style="font: 11pt Times New Roman, Times, Serif; margin: 0; text-align: justify">&nbsp;</p> 
<p style="font: 11pt Times New Roman, Times, Serif; margin: 0; text-align: justify">&nbsp;</p> 
<p style="font: 12pt Times New Roman, Times, Serif; margin: 0; text-align: justify"><font style="font-size: 11pt">Filed by the Registrant </font><font style="font-family: Wingdings; font-size: 15pt"> ¨ </font></p> 
<p style="font: 11pt Times New Roman, Times, Serif; margin: 0; text-align: justify">&nbsp;</p> 
<p style="font: 12pt Times New Roman, Times, Serif; margin: 0; text-align: justify"><font style="font-size: 11pt">Filed by a Party other than the Registrant </font><font style="font-family: Wingdings; font-size: 15pt"> þ </font></p> 
<p style="font: 11pt Times New Roman, Times, Serif; margin: 0; text-align: justify">&nbsp;</p> 
<p style="font: 11pt Times New Roman, Times, Serif; margin: 0; text-align: justify">Check the appropriate box:</p> 
<p style="font: 11pt Times New Roman, Times, Serif; margin: 0; text-align: justify">&nbsp;</p> 
<table cellspacing="0" cellpadding="0" style="width: 100%; font: 12pt Times New Roman, Times, Serif; border-collapse: collapse"> 
 <tbody>
  <tr> 
   <td style="width: 7%; padding-right: 5.4pt; padding-left: 5.4pt; text-align: center">&nbsp;?</td> 
   <td style="width: 93%; padding-right: 5.4pt; padding-left: 5.4pt"><font style="font-size: 11pt">Preliminary Proxy Statement</font></td>
  </tr> 
  <tr> 
   <td style="padding-right: 5.4pt; padding-left: 5.4pt; text-align: center">&nbsp;?</td> 
   <td style="padding-right: 5.4pt; padding-left: 5.4pt"><font style="font-size: 11pt">Confidential, for Use of the Commission Only (as permitted by Rule 14a-6(e)(2))</font></td>
  </tr> 
  <tr> 
   <td style="padding-right: 5.4pt; padding-left: 5.4pt; text-align: center">&nbsp;?</td> 
   <td style="padding-right: 5.4pt; padding-left: 5.4pt"><font style="font-size: 11pt">Definitive Proxy Statement</font></td>
  </tr> 
  <tr> 
   <td style="padding-right: 5.4pt; padding-left: 5.4pt; text-align: center">&nbsp;?</td> 
   <td style="padding-right: 5.4pt; padding-left: 5.4pt"><font style="font-size: 11pt">Definitive Additional Materials</font></td>
  </tr> 
  <tr> 
   <td style="padding-right: 5.4pt; padding-left: 5.4pt; text-align: center"><font style="font-family: Wingdings 2">R</font><font style="font-family: Wingdings"> </font></td> 
   <td style="padding-right: 5.4pt; padding-left: 5.4pt"><font style="font-size: 11pt">Soliciting Material Under Rule 14a-12</font></td>
  </tr> 
 </tbody>
</table> 
<p style="font: 11pt Times New Roman, Times, Serif; margin: 0; text-align: justify">&nbsp;</p> 
<p style="font: 18pt Times New Roman, Times, Serif; margin: 0; text-align: center"><b>United Continental Holdings, Inc.</b></p> 
<p style="font: 11pt Times New Roman, Times, Serif; margin: 0; text-align: center">(Name of Registrant as Specified In Its Charter)</p> 
<p style="font: 11pt Times New Roman, Times, Serif; margin: 0">&nbsp;</p> 
<p style="font: 11pt Times New Roman, Times, Serif; margin: 0; text-align: center"><b>Altimeter Capital Management, LP</b></p> 
<p style="font: 11pt Times New Roman, Times, Serif; margin: 0; text-align: center"><b>Altimeter Partners Fund, L.P.</b></p> 
<p style="font: 11pt Times New Roman, Times, Serif; margin: 0; text-align: center"><b>PAR Capital Management, Inc.</b></p> 
<p style="font: 11pt Times New Roman, Times, Serif; margin: 0; text-align: center"><b>PAR Group, L.P.</b></p> 
<p style="font: 11pt Times New Roman, Times, Serif; margin: 0; text-align: center"><b>PAR Investment Partners, L.P.</b></p> 
<p style="font: 11pt Times New Roman, Times, Serif; margin: 0; text-align: center"><b>Brenda Yester Baty</b></p> 
<p style="font: 11pt Times New Roman, Times, Serif; margin: 0; text-align: center"><b>Gordon Bethune</b></p> 
<p style="font: 11pt Times New Roman, Times, Serif; margin: 0; text-align: center"><b>Brad Gerstner</b></p> 
<p style="font: 11pt Times New Roman, Times, Serif; margin: 0; text-align: center"><b>Barnaby Harford</b></p> 
<p style="font: 11pt Times New Roman, Times, Serif; margin: 0; text-align: center"><b>Rodney O’Neal</b></p> 
<p style="font: 11pt Times New Roman, Times, Serif; margin: 0; text-align: center"><b>Tina Sharkey</b></p> 
<p style="font: 11pt Times New Roman, Times, Serif; margin: 0; text-align: center"><b>&nbsp;</b></p> 
<p style="font: 11pt Times New Roman, Times, Serif; margin: 0; text-align: center">(Name of Person(s) Filing Proxy Statement, if other than the Registrant)</p> 
<p style="font: 11pt Times New Roman, Times, Serif; margin: 0; text-align: justify">&nbsp;</p> 
<p style="font: 11pt Times New Roman, Times, Serif; margin: 0; text-align: justify">&nbsp;</p> <!-- Field: Page; Sequence: 1 --> 
<div style="margin-bottom: 6pt">
 <table cellpadding="0" cellspacing="0" style="width: 100%">
  <tbody>
   <tr>
    <td style="text-align: center; width: 100%">&nbsp;</td>
   </tr>
  </tbody>
 </table>
</div> 
<div style="page-break-before: always; margin-top: 6pt">
 <table cellpadding="0" cellspacing="0" style="width: 100%">
  <tbody>
   <tr>
    <td style="text-align: center; width: 100%">&nbsp;</td>
   </tr>
  </tbody>
 </table>
</div> <!-- Field: /Page --> 
<p style="font: 10pt/85% Times New Roman, Times, Serif; margin: 0; text-align: justify">Payment of Filing Fee (check the appropriate box):</p> 
<p style="font: 10pt/85% Times New Roman, Times, Serif; margin: 0; text-align: justify">&nbsp;</p> 
<table cellspacing="0" cellpadding="0" style="width: 100%; font: 12pt Times New Roman, Times, Serif; border-collapse: collapse"> 
 <tbody>
  <tr> 
   <td style="width: 7%; padding-right: 5.4pt; padding-left: 5.4pt; text-align: center">&nbsp;<font style="font-family: Wingdings 2">R</font></td> 
   <td style="width: 93%; padding-right: 5.4pt; padding-left: 5.4pt"><font style="font-size: 10pt; line-height: 85%">No fee required.</font></td>
  </tr> 
  <tr> 
   <td style="padding-right: 5.4pt; padding-left: 5.4pt">&nbsp;</td> 
   <td style="padding-right: 5.4pt; padding-left: 5.4pt">&nbsp;</td>
  </tr> 
  <tr> 
   <td style="padding-right: 5.4pt; padding-left: 5.4pt; text-align: center">?</td> 
   <td style="padding-right: 5.4pt; padding-left: 5.4pt"><font style="font-size: 10pt; line-height: 85%">Fee computed on table below per Exchange Act Rule 14a-6(i)(4) and 0-11.</font></td>
  </tr> 
 </tbody>
</table> 
<p style="font: 10pt/85% Times New Roman, Times, Serif; margin: 0; text-align: justify">&nbsp;</p> 
<table cellspacing="0" cellpadding="0" style="width: 100%; font: 12pt Times New Roman, Times, Serif; border-collapse: collapse"> 
 <tbody>
  <tr style="vertical-align: top"> 
   <td style="width: 7%; padding-right: 5.4pt; padding-left: 5.4pt; text-align: justify">&nbsp;</td> 
   <td style="width: 9%; padding-right: 5.4pt; padding-left: 5.4pt; text-align: justify"><font style="font-size: 10pt; line-height: 85%">1)</font></td> 
   <td style="width: 84%; padding-right: 5.4pt; padding-left: 5.4pt; text-align: justify"><font style="font-size: 10pt; line-height: 85%">Title of each class of securities to which transaction applies:</font></td>
  </tr> 
  <tr style="vertical-align: top"> 
   <td style="padding-right: 5.4pt; padding-left: 5.4pt; text-align: justify">&nbsp;</td> 
   <td style="padding-right: 5.4pt; padding-left: 5.4pt; text-align: justify">&nbsp;</td> 
   <td style="padding-right: 5.4pt; padding-left: 5.4pt; text-align: justify">&nbsp;</td>
  </tr> 
  <tr style="vertical-align: top"> 
   <td style="padding-right: 5.4pt; padding-left: 5.4pt; text-align: justify">&nbsp;</td> 
   <td style="padding-right: 5.4pt; padding-left: 5.4pt; text-align: justify">&nbsp;</td> 
   <td style="padding-right: 5.4pt; padding-left: 5.4pt; text-align: justify">&nbsp;</td>
  </tr> 
  <tr style="vertical-align: top"> 
   <td style="padding-right: 5.4pt; padding-left: 5.4pt; text-align: justify">&nbsp;</td> 
   <td style="padding-right: 5.4pt; padding-left: 5.4pt; text-align: justify">&nbsp;</td> 
   <td style="padding-right: 5.4pt; padding-left: 5.4pt; text-align: justify">&nbsp;</td>
  </tr> 
  <tr style="vertical-align: top"> 
   <td style="padding-right: 5.4pt; padding-left: 5.4pt; text-align: justify">&nbsp;</td> 
   <td style="padding-right: 5.4pt; padding-left: 5.4pt; text-align: justify"><font style="font-size: 10pt; line-height: 85%">2)</font></td> 
   <td style="padding-right: 5.4pt; padding-left: 5.4pt; text-align: justify"><font style="font-size: 10pt; line-height: 85%">Aggregate number of securities to which transaction applies:</font></td>
  </tr> 
  <tr style="vertical-align: top"> 
   <td style="padding-right: 5.4pt; padding-left: 5.4pt; text-align: justify">&nbsp;</td> 
   <td style="padding-right: 5.4pt; padding-left: 5.4pt; text-align: justify">&nbsp;</td> 
   <td style="padding-right: 5.4pt; padding-left: 5.4pt; text-align: justify">&nbsp;</td>
  </tr> 
  <tr style="vertical-align: top"> 
   <td style="padding-right: 5.4pt; padding-left: 5.4pt; text-align: justify">&nbsp;</td> 
   <td style="padding-right: 5.4pt; padding-left: 5.4pt; text-align: justify">&nbsp;</td> 
   <td style="padding-right: 5.4pt; padding-left: 5.4pt; text-align: justify">&nbsp;</td>
  </tr> 
 </tbody>
</table> 
<p style="font: 10pt Times New Roman, Times, Serif; margin: 0">&nbsp;</p> 
<table cellspacing="0" cellpadding="0" style="width: 100%; font: 12pt Times New Roman, Times, Serif; border-collapse: collapse"> 
 <tbody>
  <tr style="vertical-align: top"> 
   <td style="width: 7%; padding-right: 5.4pt; padding-left: 5.4pt; text-align: justify">&nbsp;</td> 
   <td style="width: 9%; padding-right: 5.4pt; padding-left: 5.4pt; text-align: justify"><font style="font-size: 10pt">3)</font></td> 
   <td style="width: 84%; padding-right: 5.4pt; padding-left: 5.4pt; text-align: justify"><font style="font-size: 10pt">Per unit price or other underlying value of transaction computed pursuant to Exchange Act</font></td>
  </tr> 
  <tr style="vertical-align: top"> 
   <td colspan="3" style="padding-right: 5.4pt; padding-left: 5.4pt; text-align: justify"><font style="font-size: 10pt">Rule 0-11 (set forth the amount on which the filing fee is calculated and state how it was determined):</font></td>
  </tr> 
 </tbody>
</table> 
<p style="font: 10pt Times New Roman, Times, Serif; margin: 0">&nbsp;</p> 
<table cellspacing="0" cellpadding="0" style="width: 100%; font: 12pt Times New Roman, Times, Serif; border-collapse: collapse"> 
 <tbody>
  <tr style="vertical-align: top"> 
   <td style="width: 7%; padding-right: 5.4pt; padding-left: 5.4pt; text-align: justify">&nbsp;</td> 
   <td style="width: 9%; padding-right: 5.4pt; padding-left: 5.4pt; text-align: justify">&nbsp;</td> 
   <td style="width: 84%; padding-right: 5.4pt; padding-left: 5.4pt; text-align: justify">&nbsp;</td>
  </tr> 
  <tr style="vertical-align: top"> 
   <td style="padding-right: 5.4pt; padding-left: 5.4pt; text-align: justify">&nbsp;</td> 
   <td style="padding-right: 5.4pt; padding-left: 5.4pt; text-align: justify">&nbsp;</td> 
   <td style="padding-right: 5.4pt; padding-left: 5.4pt; text-align: justify">&nbsp;</td>
  </tr> 
  <tr style="vertical-align: top"> 
   <td style="padding-right: 5.4pt; padding-left: 5.4pt; text-align: justify">&nbsp;</td> 
   <td style="padding-right: 5.4pt; padding-left: 5.4pt; text-align: justify"><font style="font-size: 10pt; line-height: 85%">4)</font></td> 
   <td style="padding-right: 5.4pt; padding-left: 5.4pt; text-align: justify"><font style="font-size: 10pt; line-height: 85%">Proposed maximum aggregate value of transaction:</font></td>
  </tr> 
  <tr style="vertical-align: top"> 
   <td style="padding-right: 5.4pt; padding-left: 5.4pt; text-align: justify">&nbsp;</td> 
   <td style="padding-right: 5.4pt; padding-left: 5.4pt; text-align: justify">&nbsp;</td> 
   <td style="padding-right: 5.4pt; padding-left: 5.4pt; text-align: justify">&nbsp;</td>
  </tr> 
  <tr style="vertical-align: top"> 
   <td style="padding-right: 5.4pt; padding-left: 5.4pt; text-align: justify">&nbsp;</td> 
   <td style="padding-right: 5.4pt; padding-left: 5.4pt; text-align: justify">&nbsp;</td> 
   <td style="padding-right: 5.4pt; padding-left: 5.4pt; text-align: justify">&nbsp;</td>
  </tr> 
  <tr style="vertical-align: top"> 
   <td style="padding-right: 5.4pt; padding-left: 5.4pt; text-align: justify">&nbsp;</td> 
   <td style="padding-right: 5.4pt; padding-left: 5.4pt; text-align: justify">&nbsp;</td> 
   <td style="padding-right: 5.4pt; padding-left: 5.4pt; text-align: justify">&nbsp;</td>
  </tr> 
  <tr style="vertical-align: top"> 
   <td style="padding-right: 5.4pt; padding-left: 5.4pt; text-align: justify">&nbsp;</td> 
   <td style="padding-right: 5.4pt; padding-left: 5.4pt; text-align: justify"><font style="font-size: 10pt; line-height: 85%">5)</font></td> 
   <td style="padding-right: 5.4pt; padding-left: 5.4pt; text-align: justify"><font style="font-size: 10pt; line-height: 85%">Total fee paid:</font></td>
  </tr> 
  <tr style="vertical-align: top"> 
   <td style="padding-right: 5.4pt; padding-left: 5.4pt; text-align: justify">&nbsp;</td> 
   <td style="padding-right: 5.4pt; padding-left: 5.4pt; text-align: justify">&nbsp;</td> 
   <td style="padding-right: 5.4pt; padding-left: 5.4pt; text-align: justify">&nbsp;</td>
  </tr> 
  <tr style="vertical-align: top"> 
   <td style="padding-right: 5.4pt; padding-left: 5.4pt; text-align: justify">&nbsp;</td> 
   <td style="padding-right: 5.4pt; padding-left: 5.4pt; text-align: justify">&nbsp;</td> 
   <td style="padding-right: 5.4pt; padding-left: 5.4pt; text-align: justify">&nbsp;</td>
  </tr> 
  <tr style="vertical-align: top"> 
   <td style="padding-right: 5.4pt; padding-left: 5.4pt; text-align: justify">&nbsp;</td> 
   <td style="padding-right: 5.4pt; padding-left: 5.4pt; text-align: justify">&nbsp;</td> 
   <td style="padding-right: 5.4pt; padding-left: 5.4pt; text-align: justify">&nbsp;</td>
  </tr> 
 </tbody>
</table> 
<p style="font: 10pt Times New Roman, Times, Serif; margin: 0">&nbsp;</p> 
<table cellspacing="0" cellpadding="0" style="width: 100%; font: 12pt Times New Roman, Times, Serif; border-collapse: collapse"> 
 <tbody>
  <tr> 
   <td style="width: 7%; padding-right: 5.4pt; padding-left: 5.4pt; text-align: center">?</td> 
   <td style="width: 93%; padding-right: 5.4pt; padding-left: 5.4pt"><font style="font-size: 10pt; line-height: 85%">Fee paid previously with preliminary materials.</font></td>
  </tr> 
 </tbody>
</table> 
<p style="font: 10pt Times New Roman, Times, Serif; margin: 0">&nbsp;</p> 
<table cellspacing="0" cellpadding="0" style="width: 100%; font: 12pt Times New Roman, Times, Serif; border-collapse: collapse"> 
 <tbody>
  <tr> 
   <td style="width: 7%; padding-right: 5.4pt; padding-left: 5.4pt; text-align: center">?</td> 
   <td style="width: 93%; padding-right: 5.4pt; padding-left: 5.4pt"><font style="font-size: 10pt">Check box if any part of the fee is offset as provided by Exchange Act Rule 0-11(a)(2) and identify the</font></td>
  </tr> 
  <tr style="vertical-align: top"> 
   <td colspan="2" style="padding-right: 5.4pt; padding-left: 5.4pt; text-align: justify"><font style="font-size: 10pt">filing for which the offsetting fee was paid previously.&nbsp;&nbsp;Identify the previous filing by registration statement number, or the Form or Schedule and the date of its filing.</font></td>
  </tr> 
 </tbody>
</table> 
<p style="font: 10pt Times New Roman, Times, Serif; margin: 0">&nbsp;</p> 
<table cellspacing="0" cellpadding="0" style="width: 100%; font: 12pt Times New Roman, Times, Serif; border-collapse: collapse"> 
 <tbody>
  <tr style="vertical-align: top"> 
   <td style="width: 7%; padding-right: 5.4pt; padding-left: 5.4pt; text-align: justify">&nbsp;</td> 
   <td style="width: 9%; padding-right: 5.4pt; padding-left: 5.4pt; text-align: justify"><font style="font-size: 10pt; line-height: 85%">1)</font></td> 
   <td style="width: 84%; padding-right: 5.4pt; padding-left: 5.4pt; text-align: justify"><font style="font-size: 10pt; line-height: 85%">Amount Previously Paid:</font></td>
  </tr> 
  <tr style="vertical-align: top"> 
   <td style="padding-right: 5.4pt; padding-left: 5.4pt; text-align: justify">&nbsp;</td> 
   <td style="padding-right: 5.4pt; padding-left: 5.4pt; text-align: justify">&nbsp;</td> 
   <td style="padding-right: 5.4pt; padding-left: 5.4pt; text-align: justify">&nbsp;</td>
  </tr> 
  <tr style="vertical-align: top"> 
   <td style="padding-right: 5.4pt; padding-left: 5.4pt; text-align: justify">&nbsp;</td> 
   <td style="padding-right: 5.4pt; padding-left: 5.4pt; text-align: justify">&nbsp;</td> 
   <td style="padding-right: 5.4pt; padding-left: 5.4pt; text-align: justify">&nbsp;</td>
  </tr> 
  <tr style="vertical-align: top"> 
   <td style="padding-right: 5.4pt; padding-left: 5.4pt; text-align: justify">&nbsp;</td> 
   <td style="padding-right: 5.4pt; padding-left: 5.4pt; text-align: justify">&nbsp;</td> 
   <td style="padding-right: 5.4pt; padding-left: 5.4pt; text-align: justify">&nbsp;</td>
  </tr> 
  <tr style="vertical-align: top"> 
   <td style="padding-right: 5.4pt; padding-left: 5.4pt; text-align: justify">&nbsp;</td> 
   <td style="padding-right: 5.4pt; padding-left: 5.4pt; text-align: justify"><font style="font-size: 10pt; line-height: 85%">2)</font></td> 
   <td style="padding-right: 5.4pt; padding-left: 5.4pt; text-align: justify"><font style="font-size: 10pt; line-height: 85%">Form, Schedule or Registration Statement No.:</font></td>
  </tr> 
  <tr style="vertical-align: top"> 
   <td style="padding-right: 5.4pt; padding-left: 5.4pt; text-align: justify">&nbsp;</td> 
   <td style="padding-right: 5.4pt; padding-left: 5.4pt; text-align: justify">&nbsp;</td> 
   <td style="padding-right: 5.4pt; padding-left: 5.4pt; text-align: justify">&nbsp;</td>
  </tr> 
  <tr style="vertical-align: top"> 
   <td style="padding-right: 5.4pt; padding-left: 5.4pt; text-align: justify">&nbsp;</td> 
   <td style="padding-right: 5.4pt; padding-left: 5.4pt; text-align: justify">&nbsp;</td> 
   <td style="padding-right: 5.4pt; padding-left: 5.4pt; text-align: justify">&nbsp;</td>
  </tr> 
  <tr style="vertical-align: top"> 
   <td style="padding-right: 5.4pt; padding-left: 5.4pt; text-align: justify">&nbsp;</td> 
   <td style="padding-right: 5.4pt; padding-left: 5.4pt; text-align: justify">&nbsp;</td> 
   <td style="padding-right: 5.4pt; padding-left: 5.4pt; text-align: justify">&nbsp;</td>
  </tr> 
  <tr style="vertical-align: top"> 
   <td style="padding-right: 5.4pt; padding-left: 5.4pt; text-align: justify">&nbsp;</td> 
   <td style="padding-right: 5.4pt; padding-left: 5.4pt; text-align: justify"><font style="font-size: 10pt; line-height: 85%">3)</font></td> 
   <td style="padding-right: 5.4pt; padding-left: 5.4pt; text-align: justify"><font style="font-size: 10pt; line-height: 85%">Filing Party:</font></td>
  </tr> 
  <tr style="vertical-align: top"> 
   <td style="padding-right: 5.4pt; padding-left: 5.4pt; text-align: justify">&nbsp;</td> 
   <td style="padding-right: 5.4pt; padding-left: 5.4pt; text-align: justify">&nbsp;</td> 
   <td style="padding-right: 5.4pt; padding-left: 5.4pt; text-align: justify">&nbsp;</td>
  </tr> 
  <tr style="vertical-align: top"> 
   <td style="padding-right: 5.4pt; padding-left: 5.4pt; text-align: justify">&nbsp;</td> 
   <td style="padding-right: 5.4pt; padding-left: 5.4pt; text-align: justify">&nbsp;</td> 
   <td style="padding-right: 5.4pt; padding-left: 5.4pt; text-align: justify">&nbsp;</td>
  </tr> 
  <tr style="vertical-align: top"> 
   <td style="padding-right: 5.4pt; padding-left: 5.4pt; text-align: justify">&nbsp;</td> 
   <td style="padding-right: 5.4pt; padding-left: 5.4pt; text-align: justify">&nbsp;</td> 
   <td style="padding-right: 5.4pt; padding-left: 5.4pt; text-align: justify">&nbsp;</td>
  </tr> 
  <tr style="vertical-align: top"> 
   <td style="padding-right: 5.4pt; padding-left: 5.4pt; text-align: justify">&nbsp;</td> 
   <td style="padding-right: 5.4pt; padding-left: 5.4pt; text-align: justify"><font style="font-size: 10pt; line-height: 85%">4)</font></td> 
   <td style="padding-right: 5.4pt; padding-left: 5.4pt; text-align: justify"><font style="font-size: 10pt; line-height: 85%">Date Filed:</font></td>
  </tr> 
 </tbody>
</table> <!-- Field: Page; Sequence: 2 --> 
<div style="margin-bottom: 6pt">
 <table cellpadding="0" cellspacing="0" style="width: 100%">
  <tbody>
   <tr>
    <td style="text-align: center; width: 100%">&nbsp;</td>
   </tr>
  </tbody>
 </table>
</div> 
<div style="page-break-before: always; margin-top: 6pt">
 <table cellpadding="0" cellspacing="0" style="width: 100%">
  <tbody>
   <tr>
    <td style="text-align: center; width: 100%">&nbsp;</td>
   </tr>
  </tbody>
 </table>
</div> <!-- Field: /Page --> 
<p style="font: 12pt Times New Roman, Times, Serif; margin: 0">On April 5, 2016, Altimeter Capital Management, LP and its affiliates (“ACM”) and PAR Capital Management, Inc. issued a press release (the “Press Release”) announcing the launch of the campaign website www.UnitedCourseCorrection.com (the “Website”). A copy of the Press Release is filed herewith as Exhibit 1.</p> 
<p style="font: 12pt Times New Roman, Times, Serif; margin: 0">&nbsp;</p> 
<p style="font: 12pt Times New Roman, Times, Serif; margin: 0">Copies of the materials posted to the Website are filed herewith as Exhibit 2. Other than the materials filed herewith, all materials posted to the Website that are required to be filed as soliciting material on Schedule 14A have been previously filed by ACM with the Securities and Exchange Commission on Schedule 14A.</p> 
<p style="font: 12pt Times New Roman, Times, Serif; margin: 0">&nbsp;</p>